setup.py
comp_exp/__init__.py
comp_exp.egg-info/PKG-INFO
comp_exp.egg-info/SOURCES.txt
comp_exp.egg-info/dependency_links.txt
comp_exp.egg-info/not-zip-safe
comp_exp.egg-info/top_level.txt
comp_exp/experimenters/__init__.py
comp_exp/experimenters/base.py
comp_exp/experimenters/common.py
comp_exp/experimenters/pure.py
comp_exp/experimenters/with_hdf5.py
comp_exp/experimenters/with_pandas.py
comp_exp/experiments_data/__init__.py
comp_exp/experiments_data/experiment_data.py
comp_exp/experiments_data/experiment_step_data.py
comp_exp/experiments_data/experiments_data.py
comp_exp/experiments_data/experiments_sql.py
comp_exp/experiments_data/numpy_field_data.py
comp_exp/experiments_data/utils.py