Metadata-Version: 1.1
Name: comp-exp
Version: 2.3.1
Summary: Flexible computational experiments framework
Home-page: https://hg.plav.in/my_projects/python/comp-exp
Author: Alexander Plavin
Author-email: alexander@plav.in
License: MIT
Keywords: scientific computation experiment
Platform: UNKNOWN
Classifier: Development Status :: 4 - Beta
Classifier: Intended Audience :: Developers
Classifier: Intended Audience :: Science/Research
Classifier: License :: OSI Approved :: MIT License
Classifier: Natural Language :: English
Classifier: Operating System :: OS Independent
Classifier: Programming Language :: Python :: 2.7
Classifier: Topic :: Scientific/Engineering :: Information Analysis
Classifier: Topic :: Software Development :: Libraries :: Python Modules
